{
  "class_name": "Neutralize",
  "title": "Neutralize",
  "character": "Silent",
  "energy_cost": 0,
  "type": "Attack",
  "rarity": "Basic",
  "target": "Single",
  "keywords": [],
  "vars": [
    {
      "type": "Damage",
      "base_value": 3,
      "upgraded_value": 4
    },
    {
      "type": "Weak",
      "base_value": 1,
      "upgraded_value": 2
    }
  ],
  "description": "Deal 3 damage.\nApply 1 [gold]Weak[/gold].",
  "upgraded_description": "Deal 4 damage.\nApply 2 [gold]Weak[/gold].",
  "referenced_powers": [
    {
      "class_name": "WeakPower",
      "title": "Weak",
      "slug": "weak"
    }
  ]
}
