{
  "class_name": "Quasar",
  "title": "Quasar",
  "character": "Colorless",
  "energy_cost": 0,
  "type": "Skill",
  "rarity": "Uncommon",
  "target": "Self",
  "keywords": [],
  "vars": [],
  "description": "Choose 1 of 3 random Colorless cards to add into your [gold]Hand[/gold].",
  "upgraded_description": "Choose 1 of 3 random [gold]Upgraded[/gold] Colorless cards to add into your [gold]Hand[/gold].",
  "star_cost": 2,
  "x_cost": false,
  "referenced_powers": [],
  "notes": "Offers a choice between 3 random Colorless cards to add to hand. If the card is Upgraded, the offered cards are Upgraded."
}
