{
  "class_name": "StoneOfAllTime",
  "title": "Stone of All Time",
  "description": "A massive boulder sits in the middle of an abandoned courtyard.\n\nA plaque reads:\n[gold][b]Stone of All Time[/b][/gold].\n\nIts presence, shape, and adornments indicate that this courtyard was built around this [blue]Stone[/blue] and that it has never moved from this spot.",
  "options": [
    {
      "title": "Drink and Lift",
      "description": "Lose [red][a random potion from your inventory][/red]. Gain [blue]10[/blue] Max HP.",
      "requires": "At least one potion in inventory"
    },
    {
      "title": "Push",
      "description": "Lose [red]6[/red] HP. [gold]Enchant[/gold] an Attack with [purple]Vigorous[/purple] [blue]8[/blue].",
      "requires": "At least one Attack card in deck"
    }
  ],
  "acts": ["Glory", "Hive", "Overgrowth", "Underdocks"],
  "conditions": ["Act 2 only", "All players must have at least one potion"],
  "notes": "Both options present flavor text that suggests nothing actually happens—a reference to a famous scene from Earthbound. The LIFT option consumes a randomly selected potion from your inventory and increases your Max HP. The PUSH option deals damage and allows you to enchant one Attack card with [purple]Vigorous[/purple], which increases damage and grants [green]Block[/green] on attacks.",
  "card_refs": [],
  "relic_refs": []
}
